spy/tab.py
spytopsis-1.0.0.dist-info/LICENSE
spytopsis-1.0.0.dist-info/LICENSE.py
spytopsis-1.0.0.dist-info/METADATA
spytopsis-1.0.0.dist-info/WHEEL
spytopsis-1.0.0.dist-info/entry_points.txt
spytopsis-1.0.0.dist-info/top_level.txt
spytopsis-1.0.0.dist-info/RECORD
